nameutils/__init__.py
nameutils/nameutils.py
nameutils-1.0.1.dist-info/METADATA
nameutils-1.0.1.dist-info/WHEEL
nameutils-1.0.1.dist-info/licenses/LICENSE
nameutils-1.0.1.dist-info/RECORD
