Metadata-Version: 2.4
Name: nameutils
Version: 1.0.1
Summary: Identify family/given names and capitalize correctly
Project-URL: Documentation, https://raf.org/nameutils/manual/nameutils.3py.html
Project-URL: Repository, https://github.com/rafmod/nameutils
Project-URL: Bug Tracker, https://github.com/rafmod/nameutils/issues
Author-email: raf <raf@raf.org>
Maintainer-email: raf <raf@raf.org>
License:                     GNU GENERAL PUBLIC LICENSE
License-File: LICENSE
Classifier: Development Status :: 5 - Production/Stable
Classifier: License :: OSI Approved :: GNU General Public License v3 or later (GPLv3+)
Classifier: Operating System :: OS Independent
Classifier: Programming Language :: Python :: 3
Classifier: Topic :: Text Processing :: Linguistic
Requires-Python: >=3.0
Requires-Dist: regex
